interfaces/gradio/app.py
interfaces/gradio/config.py
interfaces/gradio/utils.py
interfaces/gradio/visualization.py
interfaces/streamlit/app.py
interfaces/streamlit/config.py
interfaces/streamlit/layout.py
interfaces/streamlit/utils.py
interfaces/streamlit/visualization.py
sentiment_emotion_detection-0.1.0.dist-info/METADATA
sentiment_emotion_detection-0.1.0.dist-info/WHEEL
sentiment_emotion_detection-0.1.0.dist-info/RECORD
