Metadata-Version: 2.3
Name: sentiment-emotion-detection
Version: 0.1.0
Summary: Add your description here
Requires-Python: >=3.9.18
Requires-Dist: gradio>=4.42.0
Requires-Dist: langchain-together>=0.1.5
Requires-Dist: numpy==1.24.4
Requires-Dist: plotly>=5.23.0
Requires-Dist: streamlit>=1.37.1
Requires-Dist: torch>=2.4.0
Requires-Dist: transformers>=4.44.2
